avault/__init__.py
avault/avault.py
avault-0.1.3.dist-info/entry_points.txt
avault-0.1.3.dist-info/LICENSE
avault-0.1.3.dist-info/WHEEL
avault-0.1.3.dist-info/METADATA
avault-0.1.3.dist-info/RECORD
