Metadata-Version: 2.1
Name: avault
Version: 0.1.3
Summary: 
Home-page: https://github.com/fkshom
License: MIT
Author: Shoma FUKUDA
Author-email: fkshom+pypi@gmail.com
Requires-Python: >=3.6,<4.0
Classifier: Development Status :: 3 - Alpha
Classifier: Environment :: Console
Classifier: Intended Audience :: Developers
Classifier: License :: OSI Approved :: MIT License
Classifier: Programming Language :: Python :: 3
Classifier: Programming Language :: Python :: 3.6
Classifier: Programming Language :: Python :: 3.7
Classifier: Programming Language :: Python :: 3.8
Classifier: Topic :: Utilities
Requires-Dist: ansible (>=2.5,<3.0)
Requires-Dist: cryptography (>=3.4.6,<4.0.0)
Requires-Dist: jinja2 (>=2.11.3,<3.0.0)
Requires-Dist: pyyaml (>=5.4.1,<6.0.0)
Project-URL: Documentation, https://github.com/fkshom/avault
Project-URL: Repository, https://github.com/fkshom/avault
